README.rst
setup.py
toredis/__init__.py
toredis/_compat.py
toredis/client.py
toredis/commands.py
toredis/errors.py
toredis/pipeline.py
toredis/pool.py
yatoredis.egg-info/PKG-INFO
yatoredis.egg-info/SOURCES.txt
yatoredis.egg-info/dependency_links.txt
yatoredis.egg-info/requires.txt
yatoredis.egg-info/top_level.txt