Metadata-Version: 1.0
Name: yatoredis
Version: 0.1.3
Summary: Yet Another toredis, Client Pool Supported. Forked From https://github.com/mrjoes/toredis/
Home-page: http://github.com/bufferx/toredis/
Author: ZY ZHANG
Author-email: idup2x@gmail.com
License: http://www.apache.org/licenses/LICENSE-2.0
Keywords: tornado,redis,hiredis,tornado redis
Platform: UNKNOWN
